{"chunk_definitions":[{"row":18,"row_count":1,"visible":true,"expansion_state":0,"options":{"engine":"r","label":"setup","include":false},"document_id":"427CB14B","chunk_id":"csetup_chunk","chunk_label":"setup"},{"row":31,"row_count":1,"visible":true,"expansion_state":0,"options":{"engine":"python","label":"unnamed-chunk-252"},"document_id":"427CB14B","chunk_id":"cf35k9mbtijhp","chunk_label":"unnamed-chunk-1"},{"row":126,"row_count":1,"visible":true,"expansion_state":0,"options":{"engine":"python","label":"unnamed-chunk-9"},"document_id":"427CB14B","chunk_id":"c1133clf7pu6y","chunk_label":"unnamed-chunk-2"},{"row":716,"row_count":1,"visible":true,"expansion_state":0,"options":{"engine":"r","label":"unnamed-chunk-53"},"document_id":"427CB14B","chunk_id":"cq6aq9jwvx9s5","chunk_label":"unnamed-chunk-4"},{"row":818,"row_count":1,"visible":true,"expansion_state":0,"options":{"engine":"python","label":"unnamed-chunk-58"},"document_id":"427CB14B","chunk_id":"c4gutiy8t4p0i","chunk_label":"unnamed-chunk-5"},{"row":1146,"row_count":1,"visible":true,"expansion_state":0,"options":{"engine":"python","label":"unnamed-chunk-61"},"document_id":"427CB14B","chunk_id":"cio6ci07jhvnz","chunk_label":"unnamed-chunk-6"},{"row":1421,"row_count":1,"visible":true,"expansion_state":0,"options":{"engine":"r","label":"unnamed-chunk-200"},"document_id":"427CB14B","chunk_id":"czp8uqkw74jab","chunk_label":"unnamed-chunk-7"},{"row":1523,"row_count":1,"visible":true,"expansion_state":0,"options":{"engine":"python","label":"unnamed-chunk-206"},"document_id":"427CB14B","chunk_id":"cs9hjikf5czyq","chunk_label":"unnamed-chunk-8"},{"row":2140,"row_count":1,"visible":true,"expansion_state":0,"options":{"engine":"r","label":"unnamed-chunk-246"},"document_id":"427CB14B","chunk_id":"cepw4quuy1uxs","chunk_label":"unnamed-chunk-10"},{"row":2201,"row_count":1,"visible":true,"expansion_state":0,"options":{"engine":"r","label":"unnamed-chunk-263"},"document_id":"427CB14B","chunk_id":"c9fmbkv0n7brc","chunk_label":"unnamed-chunk-11"}],"doc_write_time":1661827026,"working_dir":null,"default_chunk_options":{"echo":true}}